weighted_pod/__init__.py
weighted_pod/core.py
weighted_pod/utils.py
weighted_pod/visualization.py
weighted_pod-0.0.36.dist-info/METADATA
weighted_pod-0.0.36.dist-info/WHEEL
weighted_pod-0.0.36.dist-info/top_level.txt
weighted_pod-0.0.36.dist-info/RECORD
