Metadata-Version: 2.1
Name: weighted-pod
Version: 0.0.36
Summary: Proper Orthogonal Decomposition with weighted inner products for CFD analysis
Home-page: https://github.com/XXXXXXXXXX/weighted-pod
Author: Hakan Demir
Author-email: muhammet.demir@ruhr-uni-bochum.de
License: UNKNOWN
Platform: UNKNOWN
Classifier: Topic :: Scientific/Engineering
